pykomfovent/__init__.py
pykomfovent/client.py
pykomfovent/discovery.py
pykomfovent/models.py
pykomfovent/parser.py
pykomfovent/py.typed
pykomfovent-1.0.2.dist-info/METADATA
pykomfovent-1.0.2.dist-info/WHEEL
pykomfovent-1.0.2.dist-info/licenses/LICENSE
pykomfovent-1.0.2.dist-info/RECORD
