Metadata-Version: 2.4
Name: pykomfovent
Version: 1.0.2
Summary: Python client for Komfovent C6 ventilation units
Project-URL: Homepage, https://github.com/mostaszewski/pykomfovent
Project-URL: Repository, https://github.com/mostaszewski/pykomfovent
Project-URL: Issues, https://github.com/mostaszewski/pykomfovent/issues
Author: Mateusz Ostaszewski
License: MIT
License-File: LICENSE
Keywords: home-assistant,hvac,komfovent,ventilation
Classifier: Development Status :: 5 - Production/Stable
Classifier: Intended Audience :: Developers
Classifier: License :: OSI Approved :: MIT License
Classifier: Programming Language :: Python :: 3.11
Classifier: Programming Language :: Python :: 3.12
Classifier: Programming Language :: Python :: 3.13
Classifier: Topic :: Home Automation
Requires-Python: >=3.11
Requires-Dist: aiohttp>=3.11.0
